neatoo/__init__.py
neatoo/cli.py
neatoo-0.1.1.dist-info/METADATA
neatoo-0.1.1.dist-info/WHEEL
neatoo-0.1.1.dist-info/entry_points.txt
neatoo-0.1.1.dist-info/licenses/LICENSE
neatoo-0.1.1.dist-info/RECORD
