Metadata-Version: 2.4
Name: neatoo
Version: 0.1.1
Summary: A simple yet powerful tool for Python code formatting, checking, and testing.
Project-URL: Homepage, https://github.com/linkedlist771/neatoo
Project-URL: Repository, https://github.com/linkedlist771/neatoo.git
Author-email: linkedlist771 <213193509seu@gmail.com>
License: MIT
License-File: LICENSE
Requires-Python: >=3.12
Requires-Dist: black==23.9.1
Requires-Dist: flake8>=7.1.2
Requires-Dist: isort>=6.0.0
Requires-Dist: pytest>=8.3.4
